orgafold/__main__.py
orgafold/cmd.py
orgafold/dialoguer.py
orgafold/merge.py
orgafold/orgafold.py
orgafold-0.2.0.dist-info/METADATA
orgafold-0.2.0.dist-info/WHEEL
orgafold-0.2.0.dist-info/entry_points.txt
orgafold-0.2.0.dist-info/RECORD
