Metadata-Version: 2.1
Name: orgafold
Version: 0.2.0
Summary: Quickly handle a high number of files, perhaps obtained after a disk recovery.
Home-page: https://github.com/CZ-NIC/orgafold
License: GPL-3.0-or-later
Author: Edvard Rejthar
Author-email: edvard.rejthar@nic.cz
Requires-Python: >=3.10
Classifier: License :: OSI Approved :: GNU General Public License v3 or later (GPLv3+)
Classifier: Programming Language :: Python :: 3
Classifier: Programming Language :: Python :: 3.10
Classifier: Programming Language :: Python :: 3.11
Classifier: Programming Language :: Python :: 3.12
Requires-Dist: fire
Requires-Dist: humanize
Requires-Dist: inquirer
Requires-Dist: pandas
Requires-Dist: python-magic
Requires-Dist: tqdm
